StegaSaurus/__init__.py
StegaSaurus/cli.py
StegaSaurus/read/AdvancedImageReader.py
StegaSaurus/read/AudioReader.py
StegaSaurus/read/ImageReader.py
StegaSaurus/read/RawReader.py
StegaSaurus/read/SimpleImageReader.py
StegaSaurus/read/__init__.py
StegaSaurus/write/AdvancedImageWriter.py
StegaSaurus/write/AudioWriter.py
StegaSaurus/write/ImageWriter.py
StegaSaurus/write/RawWriter.py
StegaSaurus/write/SimpleImageWriter.py
StegaSaurus/write/__init__.py
StegaSaurus-1.1.1.dist-info/LICENSE
StegaSaurus-1.1.1.dist-info/METADATA
StegaSaurus-1.1.1.dist-info/WHEEL
StegaSaurus-1.1.1.dist-info/entry_points.txt
StegaSaurus-1.1.1.dist-info/top_level.txt
StegaSaurus-1.1.1.dist-info/RECORD
