Metadata-Version: 2.1
Name: StegaSaurus
Version: 1.1.1
Summary: (Optionally) Dependency-free library for steganography (GUI and CLI included)
Home-page: https://github.com/BizTecBritain/StegaSaurus
Author: Alexander Bisland
Author-email: biztecbritain@gmail.com
Project-URL: Bug Tracker, https://github.com/BizTecBritain/StegaSaurus/issues
Classifier: Programming Language :: Python :: 3
Classifier: License :: OSI Approved :: MIT License
Classifier: Operating System :: OS Independent
Requires-Python: >=3.8
License-File: LICENSE
Requires-Dist: setuptools (>=42)
Requires-Dist: pillow (>=9.0.0)
